rjfrank/__init__.py
rjfrank-1.0.4.dist-info/METADATA
rjfrank-1.0.4.dist-info/WHEEL
rjfrank-1.0.4.dist-info/RECORD
