Metadata-Version: 2.4
Name: rjfrank
Version: 1.0.4
Summary: An honorary Python module celebrating Randy Frank.
Project-URL: Homepage, https://github.com/viseshrp/rjfrank
Author-email: Visesh Prasad <viseshrprasad@gmail.com>
License-Expression: MIT
Classifier: License :: OSI Approved :: MIT License
Classifier: Operating System :: OS Independent
Classifier: Programming Language :: Python :: 3
Requires-Python: >=3.8
